spd_api/__init__.py
spd_api/_modidx.py
spd_api/core.py
spd_api/ea.py
spd_api/spd.py
spd_api-0.0.9.dist-info/LICENSE
spd_api-0.0.9.dist-info/METADATA
spd_api-0.0.9.dist-info/WHEEL
spd_api-0.0.9.dist-info/entry_points.txt
spd_api-0.0.9.dist-info/top_level.txt
spd_api-0.0.9.dist-info/RECORD
