Metadata-Version: 2.1
Name: spd-api
Version: 0.0.9
Summary: connect and parse spd files
Home-page: https://github.com/CJP123/spd_api/
Author: Clive
Author-email: clive@gm.net.nz
License: Apache Software License 2.0
Keywords: nbdev
Platform: UNKNOWN
Classifier: Development Status :: 3 - Alpha
Classifier: Intended Audience :: Developers
Classifier: Natural Language :: English
Classifier: Programming Language :: Python :: 3.9
Classifier: Programming Language :: Python :: 3.10
Classifier: License :: OSI Approved :: Apache Software License
Requires-Python: >=3.9
License-File: LICENSE
Requires-Dist: fastcore
Requires-Dist: pandas
Requires-Dist: httpx
Requires-Dist: asyncio
Requires-Dist: lxml
Provides-Extra: dev
